mmar_carl/__init__.py
mmar_carl/chain.py
mmar_carl/executor.py
mmar_carl/llm.py
mmar_carl/models.py
mmar_carl-0.0.14.dist-info/licenses/LICENSE
mmar_carl-0.0.14.dist-info/WHEEL
mmar_carl-0.0.14.dist-info/METADATA
mmar_carl-0.0.14.dist-info/RECORD
