Metadata-Version: 2.4
Name: mmar-carl
Version: 0.0.14
Summary: Collaborative Agent Reasoning Library
Keywords: 
Author: glazkov, shaposhnikov, tagin
Author-email: glazkov <glazkov@airi.net>, shaposhnikov <shaposhnikov@airi.net>, tagin <tagin@airi.net>
License-Expression: MIT
License-File: LICENSE
Classifier: Development Status :: 4 - Beta
Classifier: Intended Audience :: Developers
Classifier: Programming Language :: Python
Classifier: Programming Language :: Python :: 3
Classifier: Programming Language :: Python :: 3 :: Only
Classifier: Programming Language :: Python :: 3.12
Classifier: Programming Language :: Python :: 3.13
Classifier: Programming Language :: Python :: 3.14
Classifier: Topic :: Documentation
Classifier: Topic :: Software Development
Classifier: Topic :: Utilities
Classifier: Typing :: Typed
Requires-Dist: faiss-cpu>=1.7.0
Requires-Dist: fastembed>=0.7.3
Requires-Dist: numpy>=1.21.0
Requires-Dist: pydantic>=2.11.7
Requires-Dist: mmar-llm~=2.0.11
Requires-Dist: mmar-mapi~=1.4.4
Requires-Dist: mmar-ptag~=1.0.20
Requires-Dist: mmar-utils~=1.1.17
Requires-Python: >=3.12
